ducktools/scriptmetadata/__init__.py
ducktools/scriptmetadata/_version.py
ducktools/scriptmetadata/py.typed
ducktools_scriptmetadata-0.2.0.dist-info/LICENSE.md
ducktools_scriptmetadata-0.2.0.dist-info/METADATA
ducktools_scriptmetadata-0.2.0.dist-info/WHEEL
ducktools_scriptmetadata-0.2.0.dist-info/top_level.txt
ducktools_scriptmetadata-0.2.0.dist-info/RECORD
